setup.py
Cyanide_And_Happiness.egg-info/PKG-INFO
Cyanide_And_Happiness.egg-info/SOURCES.txt
Cyanide_And_Happiness.egg-info/dependency_links.txt
Cyanide_And_Happiness.egg-info/requires.txt
Cyanide_And_Happiness.egg-info/top_level.txt
cynhap/__init__.py