Metadata-Version: 1.0
Name: Cyanide-And-Happiness
Version: 1.32
Summary: Automatically sets the latest Cyanide and Happiness comic as your background
Home-page: https://github.com/sacert/Cyanide-And-Happiness
Author: Stephen Kang
Author-email: stephenkang9@gmail.com
License: UNKNOWN
Platform: UNKNOWN
